google_storage_utility.py
cloud_utility-0.0.2.dist-info/LICENSE
cloud_utility-0.0.2.dist-info/METADATA
cloud_utility-0.0.2.dist-info/WHEEL
cloud_utility-0.0.2.dist-info/top_level.txt
cloud_utility-0.0.2.dist-info/RECORD
