Metadata-Version: 2.1
Name: cloud-utility
Version: 0.0.2
Summary: Package for any cloud apis
Author: Indranil Pal
License: UNKNOWN
Platform: UNKNOWN
Classifier: Programming Language :: Python :: 3
Classifier: License :: OSI Approved :: MIT License
Classifier: Operating System :: OS Independent
Requires-Python: >=3.7
License-File: LICENSE
Requires-Dist: google-cloud-storage
Requires-Dist: oauth2client
